<?xml version="1.0" encoding="UTF-8"?>
<objects serializationModel="Studio.01.08.00">
    <object class="EncodingSetting" id="{338962a8-8ee0-4209-8659-86f139b560c7}">
        <property name="encodingFormat">
            <value>3</value>
        </property>
        <property name="quality">
            <value>37</value>
        </property>
        <relationship name="platform">
            <destination>{31b495b2-9388-41d0-8b66-a9f848b761d6}</destination>
        </relationship>
        <relationship name="encodable">
            <destination>{a409c46b-72e6-4c2a-b70f-97b30899b382}</destination>
        </relationship>
    </object>
</objects>
